llm_annotator/__init__.py
llm_annotator/annotator.py
llm_annotator/utils.py
llm_annotator-0.4.0.dist-info/METADATA
llm_annotator-0.4.0.dist-info/WHEEL
llm_annotator-0.4.0.dist-info/licenses/LICENSE
llm_annotator-0.4.0.dist-info/RECORD
