Metadata-Version: 2.4
Name: llm-annotator
Version: 0.4.0
Summary: An easy-to-extend LLM annotator for robust, resumable data annotation.
Author-email: Bram Vanroy <2779410+BramVanroy@users.noreply.github.com>
License-Expression: Apache-2.0
License-File: LICENSE
Requires-Python: >=3.12
Requires-Dist: datasets<5,>=4.1.1
Requires-Dist: hf-transfer<1,>=0.1.9
Requires-Dist: hf-xet<2,>=1.1.10
Requires-Dist: mistral-common>=1.8.5
Requires-Dist: vllm<0.12,>=0.11
